CHANGELOG.txt
LICENSE.txt
MANIFEST.in
README.txt
setup.py
Examples/check_hwid.py
Examples/check_ip.py
Examples/check_password.py
Examples/check_username.py
Examples/current_time.py
Examples/encrypt_key.py
Examples/fetch_sql_data.py
Examples/geo_location.py
Examples/get_hwid.py
Examples/get_ip.py
Examples/get_sql_data.py
Examples/phone_lookup.py
Examples/portscan.py
Examples/reverse_hostname.py
Examples/send_request.py
Examples/webhook_delete.py
Examples/webhook_spammer.py
skidings/__init__.py
skidings.egg-info/PKG-INFO
skidings.egg-info/SOURCES.txt
skidings.egg-info/dependency_links.txt
skidings.egg-info/requires.txt
skidings.egg-info/top_level.txt