Metadata-Version: 1.1
Name: skidings
Version: 0.1.2
Summary: Simple module for new comers to networking and requests and mysql
Home-page: https://github.com/AeronPY/SkidingsPY-module
Author: AeronPY
Author-email: aeron1337@protonmail.com
License: MIT
Keywords: skidings
Platform: UNKNOWN
Classifier: Development Status :: 5 - Production/Stable
Classifier: Intended Audience :: Education
Classifier: Operating System :: Microsoft :: Windows :: Windows 10
Classifier: License :: OSI Approved :: MIT License
Classifier: Programming Language :: Python :: 3
